akpycalcf/__init__.py
akpycalcf/akpycalc.py
akpycalc-0.0.7.dist-info/LICENSE
akpycalc-0.0.7.dist-info/METADATA
akpycalc-0.0.7.dist-info/WHEEL
akpycalc-0.0.7.dist-info/top_level.txt
akpycalc-0.0.7.dist-info/RECORD
